<?xml version="1.0" encoding="utf-8" ?>
<dwsync>
<file name="dashboard.php" server="197.221.10.185/public_html/" local="130982288564314072" remote="131019148980000000" Dst="-1" />
<file name="ra_dashboard.php" server="197.221.10.185/public_html/" local="130828923614850024" remote="131019149060000000" Dst="-1" />
<file name="dashboard_mtl.php" server="197.221.10.185/public_html/" local="131037167250087172" remote="131037167260000000" Dst="-1" />
<file name="dashboard_ra.php" server="197.221.10.185/public_html/" local="130983083335419721" remote="131019148990000000" Dst="-1" />
<file name="dashboard_assessor.php" server="197.221.10.185/public_html/" local="130983083592609746" remote="131019148990000000" Dst="-1" />
<file name="dashboard_sect.php" server="197.221.10.185/public_html/" local="131032206841811715" remote="131032206820000000" Dst="-1" />
<file name="dashboard.php" server="129.232.136.198/public_html/" local="131215043264481662" remote="131215042800000000" Dst="0" />
<file name="dashboard_mtl.php" server="129.232.136.198/public_html/" local="131563410247659794" remote="131563410000000000" Dst="0" />
<file name="dashboard_sect.php" server="129.232.136.198/public_html/" local="131665511277258389" remote="131665510200000000" Dst="0" />
</dwsync>